{
  "name": "sybl",
  "version": "0.1.0",
  "summary": "Open-source BYOK voice dictation — speak anywhere, transcribe fast, type it in.",
  "license": null,
  "license_expression": "MIT",
  "home_page": "https://github.com/Rikhil-Nell/sybl",
  "home_page_source": "project_urls.homepage",
  "maintainer": null,
  "author": null,
  "repository": "https://github.com/Rikhil-Nell/sybl",
  "repository_source": "project_urls.repository",
  "download": null,
  "download_source": null,
  "pub_date": 1782647188,
  "project_urls": {
    "Issues": "https://github.com/Rikhil-Nell/sybl/issues",
    "Changelog": "https://github.com/Rikhil-Nell/sybl/blob/main/CHANGELOG.md",
    "Repository": "https://github.com/Rikhil-Nell/sybl",
    "Documentation": "https://github.com/Rikhil-Nell/sybl/tree/main/docs",
    "Homepage": "https://github.com/Rikhil-Nell/sybl"
  },
  "has_github_actions": true,
  "has_gitlab_pipeline": null,
  "has_dependabot": false,
  "has_pyproject_toml": true,
  "has_setup_py": false,
  "has_setup_cfg": false
}