{
  "name": "symbolite",
  "version": "1.0.0",
  "summary": "A minimalistic symbolic package.",
  "license": null,
  "license_expression": "MIT",
  "home_page": "https://github.com/dyscolab/symbolite",
  "home_page_source": "project_urls.homepage",
  "maintainer": null,
  "author": "Hernán E. Grecco, Mauro Silberberg",
  "repository": "https://github.com/dyscolab/symbolite",
  "repository_source": "project_urls.homepage",
  "download": null,
  "download_source": null,
  "pub_date": 1770751562,
  "project_urls": {
    "changelog": "https://github.com/dyscolab/symbolite/blob/main/CHANGES",
    "homepage": "https://github.com/dyscolab/symbolite",
    "issues": "https://github.com/dyscolab/symbolite/issues"
  },
  "has_github_actions": true,
  "has_gitlab_pipeline": null,
  "has_dependabot": false,
  "has_pyproject_toml": true,
  "has_setup_py": false,
  "has_setup_cfg": false
}