{
  "name": "eazydatafix",
  "version": "0.2.0",
  "summary": "A modern Python library for data quality assessment, validation, and automated data cleaning.",
  "license": null,
  "license_expression": "MIT",
  "home_page": "https://eazydatafix.com",
  "home_page_source": "project_urls.homepage",
  "maintainer": null,
  "author": "Suneel Kumar Kola",
  "repository": "https://github.com/suneelprojects/eazydatafix",
  "repository_source": "project_urls.repository",
  "download": null,
  "download_source": null,
  "pub_date": 1784467751,
  "project_urls": {
    "Repository": "https://github.com/suneelprojects/eazydatafix",
    "Documentation": "https://eazydatafix.com/docs",
    "Homepage": "https://eazydatafix.com",
    "Issues": "https://github.com/suneelprojects/eazydatafix/issues"
  },
  "has_github_actions": true,
  "has_gitlab_pipeline": null,
  "has_dependabot": false,
  "has_pyproject_toml": true,
  "has_setup_py": false,
  "has_setup_cfg": false
}