{
  "name": "dgm-fit",
  "version": "0.4.0",
  "summary": "iminuit interface for the dag-modelling framework",
  "license": null,
  "license_expression": "MIT",
  "home_page": "https://github.com/dagflow-team/dgm-fit",
  "home_page_source": "project_urls.homepage",
  "maintainer": null,
  "author": null,
  "repository": "https://github.com/dagflow-team/dgm-fit",
  "repository_source": "project_urls.repository",
  "download": null,
  "download_source": null,
  "pub_date": 1771929922,
  "project_urls": {
    "documentation": "https://github.com/dagflow-team/dgm-fit/wiki",
    "homepage": "https://github.com/dagflow-team/dgm-fit",
    "Bug Tracker": "https://github.com/dagflow-team/dgm-fit/issues",
    "repository": "https://github.com/dagflow-team/dgm-fit",
    "DAGModelling Team": "https://github.com/dagflow-team"
  },
  "has_github_actions": false,
  "has_gitlab_pipeline": null,
  "has_dependabot": false,
  "has_pyproject_toml": true,
  "has_setup_py": false,
  "has_setup_cfg": false
}