{
  "name": "agile-backlog",
  "version": "0.30.0",
  "summary": "Lightweight Kanban board tool for agentic development",
  "license": "MIT",
  "license_expression": null,
  "home_page": "https://github.com/zbarbur/agile-backlog",
  "home_page_source": "project_urls.homepage",
  "maintainer": null,
  "author": "agile-backlog contributors",
  "repository": "https://github.com/zbarbur/agile-backlog",
  "repository_source": "project_urls.repository",
  "download": null,
  "download_source": null,
  "pub_date": 1775550361,
  "project_urls": {
    "Issues": "https://github.com/zbarbur/agile-backlog/issues",
    "Homepage": "https://github.com/zbarbur/agile-backlog",
    "Repository": "https://github.com/zbarbur/agile-backlog"
  },
  "has_github_actions": true,
  "has_gitlab_pipeline": null,
  "has_dependabot": true,
  "has_pyproject_toml": true,
  "has_setup_py": false,
  "has_setup_cfg": false
}