{
  "name": "sotto",
  "version": "0.1.0",
  "summary": "Private voice transcription server — receive audio, transcribe locally, write clean text.",
  "license": null,
  "license_expression": "MIT",
  "home_page": "https://github.com/reedshea/sotto",
  "home_page_source": "project_urls.homepage",
  "maintainer": null,
  "author": "Reed Shea",
  "repository": "https://github.com/reedshea/sotto",
  "repository_source": "project_urls.repository",
  "download": null,
  "download_source": null,
  "pub_date": 1772375434,
  "project_urls": {
    "Homepage": "https://github.com/reedshea/sotto",
    "Repository": "https://github.com/reedshea/sotto"
  },
  "has_github_actions": true,
  "has_gitlab_pipeline": null,
  "has_dependabot": false,
  "has_pyproject_toml": false,
  "has_setup_py": false,
  "has_setup_cfg": false
}