{
  "name": "Adafruit-PlatformDetect",
  "version": "3.88.0",
  "summary": "Platform detection for use by libraries like Adafruit-Blinka.",
  "license": "MIT",
  "license_expression": null,
  "home_page": "https://github.com/adafruit/Adafruit_Python_PlatformDetect",
  "home_page_source": "project_urls.homepage",
  "maintainer": null,
  "author": null,
  "repository": "https://github.com/adafruit/Adafruit_Python_PlatformDetect",
  "repository_source": "project_urls.homepage",
  "download": null,
  "download_source": null,
  "pub_date": 1771959665,
  "project_urls": {
    "Homepage": "https://github.com/adafruit/Adafruit_Python_PlatformDetect"
  },
  "has_github_actions": true,
  "has_gitlab_pipeline": null,
  "has_dependabot": false,
  "has_pyproject_toml": true,
  "has_setup_py": false,
  "has_setup_cfg": false
}