{
  "name": "adafruit-circuitpython-mcp230xx",
  "version": "2.6.2",
  "summary": "CircuitPython library for controlling a MCP23008 or MCP23017 I2C GPIO expander.",
  "license": null,
  "license_expression": "MIT",
  "home_page": "https://github.com/adafruit/Adafruit_CircuitPython_MCP230xx",
  "home_page_source": "project_urls.homepage",
  "maintainer": null,
  "author": null,
  "repository": "https://github.com/adafruit/Adafruit_CircuitPython_MCP230xx",
  "repository_source": "project_urls.homepage",
  "download": null,
  "download_source": null,
  "pub_date": 1776978031,
  "project_urls": {
    "Homepage": "https://github.com/adafruit/Adafruit_CircuitPython_MCP230xx"
  },
  "has_github_actions": true,
  "has_gitlab_pipeline": null,
  "has_dependabot": false,
  "has_pyproject_toml": true,
  "has_setup_py": false,
  "has_setup_cfg": false
}