{
  "name": "rdt",
  "version": "1.20.0",
  "summary": "Reversible Data Transforms",
  "license": "BSL-1.1",
  "license_expression": null,
  "home_page": null,
  "home_page_source": null,
  "maintainer": null,
  "author": null,
  "repository": "https://github.com/sdv-dev/RDT/",
  "repository_source": "project_urls.sourcecode",
  "download": null,
  "download_source": null,
  "pub_date": 1769198854,
  "project_urls": {
    "Twitter": "https://twitter.com/sdv_dev",
    "Chat": "https://bit.ly/sdv-slack-invite",
    "Issue Tracker": "https://github.com/sdv-dev/RDT/issues",
    "Source Code": "https://github.com/sdv-dev/RDT/",
    "Changes": "https://github.com/sdv-dev/RDT/blob/main/HISTORY.md"
  },
  "has_github_actions": true,
  "has_gitlab_pipeline": null,
  "has_dependabot": false,
  "has_pyproject_toml": true,
  "has_setup_py": false,
  "has_setup_cfg": false
}