{
  "name": "ragstack-mcp",
  "version": "0.1.2.dev8",
  "summary": "MCP server for RAGStack knowledge base - search, chat, upload, and scrape",
  "license": null,
  "license_expression": "MIT",
  "home_page": null,
  "maintainer": null,
  "maintainer_email": null,
  "author": "RAGStack Team",
  "author_email": null,
  "pub_date": 1768288977,
  "project_urls": {
    "homepage": "https://github.com/HatmanStack/RAGStack-Lambda",
    "repository": "https://github.com/HatmanStack/RAGStack-Lambda",
    "github": null
  },
  "has_github_actions": true
}