{
  "name": "neon-skill-weather",
  "version": "3.1.1a4",
  "summary": null,
  "license": "BSD-3-Clause",
  "license_expression": null,
  "home_page": "https://github.com/NeonGeckoCom/skill-weather",
  "home_page_source": "project_urls.homepage",
  "maintainer": null,
  "author": "Neongecko",
  "repository": "https://github.com/NeonGeckoCom/skill-weather",
  "repository_source": "project_urls.homepage",
  "download": null,
  "download_source": null,
  "pub_date": 1773422006,
  "project_urls": {
    "Homepage": "https://github.com/NeonGeckoCom/skill-weather"
  },
  "has_github_actions": true,
  "has_gitlab_pipeline": null,
  "has_dependabot": false,
  "has_pyproject_toml": false,
  "has_setup_py": true,
  "has_setup_cfg": false
}