{
  "name": "netbox-bmc",
  "version": "0.4.19",
  "summary": "Unified out-of-band management for NetBox: Redfish & IPMI inventory sync, power control, console access",
  "license": "Apache-2.0",
  "license_expression": null,
  "home_page": null,
  "home_page_source": null,
  "maintainer": null,
  "author": "tak-labo",
  "repository": "https://github.com/tak-labo/netbox-bmc",
  "repository_source": "project_urls.source",
  "download": null,
  "download_source": null,
  "pub_date": 1782701270,
  "project_urls": {
    "Documentation": "https://github.com/tak-labo/netbox-bmc/blob/main/README.md",
    "Tracker": "https://github.com/tak-labo/netbox-bmc/issues",
    "Source": "https://github.com/tak-labo/netbox-bmc"
  },
  "has_github_actions": true,
  "has_gitlab_pipeline": null,
  "has_dependabot": false,
  "has_pyproject_toml": true,
  "has_setup_py": false,
  "has_setup_cfg": false
}