{
  "name": "nexora-db",
  "version": "0.2.2",
  "summary": "Shared database layer for Nexora monitoring platform",
  "license": null,
  "license_expression": null,
  "home_page": "https://github.com/senani-derradji",
  "home_page_source": "project_urls.homepage",
  "maintainer": "Derradji Senani",
  "author": "Derradji Senani",
  "repository": "https://github.com/senani-derradji/nexora",
  "repository_source": "project_urls.repository",
  "download": null,
  "download_source": null,
  "pub_date": 1772888160,
  "project_urls": {
    "Homepage": "https://github.com/senani-derradji",
    "Repository": "https://github.com/senani-derradji/nexora"
  },
  "has_github_actions": false,
  "has_gitlab_pipeline": null,
  "has_dependabot": false,
  "has_pyproject_toml": false,
  "has_setup_py": false,
  "has_setup_cfg": false
}