{
  "name": "oqboost",
  "version": "2.0.5",
  "summary": "OQBoost 2.0 — gradient-boosted 2D-oblique decision trees (histogram-binned, C++ backend)",
  "license": "MIT",
  "license_expression": null,
  "home_page": "https://github.com/cree1116/oqboost-2.0",
  "home_page_source": "project_urls.homepage",
  "maintainer": null,
  "author": "leejongmin",
  "repository": "https://github.com/cree1116/oqboost-2.0",
  "repository_source": "project_urls.repository",
  "download": null,
  "download_source": null,
  "pub_date": 1782214869,
  "project_urls": {
    "Repository": "https://github.com/cree1116/oqboost-2.0",
    "Homepage": "https://github.com/cree1116/oqboost-2.0",
    "Issues": "https://github.com/cree1116/oqboost-2.0/issues"
  },
  "has_github_actions": true,
  "has_gitlab_pipeline": null,
  "has_dependabot": false,
  "has_pyproject_toml": true,
  "has_setup_py": true,
  "has_setup_cfg": false
}