{
  "name": "urwid",
  "version": "4.0.4",
  "summary": "A full-featured console (xterm et al.) user interface library",
  "license": null,
  "license_expression": "LGPL-2.1-only",
  "home_page": "https://urwid.org/",
  "home_page_source": "project_urls.homepage",
  "maintainer": null,
  "author": null,
  "repository": "https://github.com/urwid/urwid",
  "repository_source": "project_urls.repository",
  "download": null,
  "download_source": null,
  "pub_date": 1783954881,
  "project_urls": {
    "Bug Tracker": "https://github.com/urwid/urwid/issues",
    "Repository": "https://github.com/urwid/urwid",
    "Homepage": "https://urwid.org/",
    "Documentation": "https://urwid.org/manual/index.html"
  },
  "has_github_actions": true,
  "has_gitlab_pipeline": null,
  "has_dependabot": true,
  "has_pyproject_toml": true,
  "has_setup_py": false,
  "has_setup_cfg": false
}