{
  "name": "nano-queue",
  "version": "0.1.1",
  "summary": "Zero-infra background jobs for Python. Runs via daemon threads and piggybacks on your existing database.",
  "license": null,
  "license_expression": null,
  "home_page": "https://github.com/fidel-c/nano-queue",
  "home_page_source": "project_urls.homepage",
  "maintainer": null,
  "author": null,
  "repository": "https://github.com/fidel-c/nano-queue",
  "repository_source": "project_urls.homepage",
  "download": null,
  "download_source": null,
  "pub_date": 1775124276,
  "project_urls": {
    "Bug Tracker": "https://github.com/fidel-c/nano-queue/issues",
    "Homepage": "https://github.com/fidel-c/nano-queue"
  },
  "has_github_actions": false,
  "has_gitlab_pipeline": null,
  "has_dependabot": false,
  "has_pyproject_toml": true,
  "has_setup_py": false,
  "has_setup_cfg": false
}