{
  "name": "QuantumTUNA",
  "version": "0.11.0",
  "summary": "A streamlined quantum chemistry program for atoms and diatomics.",
  "license": null,
  "license_expression": "MIT",
  "home_page": null,
  "home_page_source": null,
  "maintainer": null,
  "author": null,
  "repository": "https://github.com/h-brough/TUNA",
  "repository_source": "project_urls.repository",
  "download": null,
  "download_source": null,
  "pub_date": 1784415184,
  "project_urls": {
    "Documentation": "https://github.com/h-brough/TUNA/blob/main/TUNA%20Manual.pdf",
    "Changelog": "https://github.com/h-brough/TUNA/blob/main/CHANGELOG.md",
    "Repository": "https://github.com/h-brough/TUNA"
  },
  "has_github_actions": true,
  "has_gitlab_pipeline": null,
  "has_dependabot": false,
  "has_pyproject_toml": true,
  "has_setup_py": true,
  "has_setup_cfg": false
}