{
  "name": "mcp-nfe-br",
  "version": "0.3.0",
  "summary": "MCP server for Brazilian electronic invoicing (NF-e / NFC-e)",
  "license": "Apache-2.0",
  "license_expression": null,
  "home_page": "https://github.com/cmendezs/mcp-nfe-br",
  "home_page_source": "project_urls.homepage",
  "maintainer": null,
  "author": null,
  "repository": "https://github.com/cmendezs/mcp-nfe-br",
  "repository_source": "project_urls.repository",
  "download": null,
  "download_source": null,
  "pub_date": 1781514348,
  "project_urls": {
    "Issues": "https://github.com/cmendezs/mcp-nfe-br/issues",
    "Repository": "https://github.com/cmendezs/mcp-nfe-br",
    "Homepage": "https://github.com/cmendezs/mcp-nfe-br",
    "Changelog": "https://github.com/cmendezs/mcp-nfe-br/blob/main/RELEASE.md"
  },
  "has_github_actions": true,
  "has_gitlab_pipeline": null,
  "has_dependabot": false,
  "has_pyproject_toml": true,
  "has_setup_py": false,
  "has_setup_cfg": false
}