{
  "name": "factompile",
  "version": "0.1.1",
  "summary": "Factompile - A compiler for the Facto programming language that generates Factorio circuit network blueprints",
  "license": "MIT",
  "license_expression": null,
  "home_page": "https://github.com/Snagnar/Factompiler",
  "maintainer": null,
  "author": "Snagnar",
  "repository": "https://github.com/Snagnar/Factompiler",
  "repository_source": "project_urls.repository",
  "pub_date": 1768943193,
  "project_urls": {
    "Documentation": "https://github.com/Snagnar/Factompiler/tree/main/doc",
    "Issues": "https://github.com/Snagnar/Factompiler/issues",
    "Changelog": "https://github.com/Snagnar/Factompiler/releases",
    "Repository": "https://github.com/Snagnar/Factompiler",
    "Homepage": "https://github.com/Snagnar/Factompiler"
  },
  "has_github_actions": true,
  "has_gitlab_pipeline": null,
  "has_dependabot": false
}