{
  "name": "singer-sdk",
  "version": "0.54.0a9",
  "summary": "A framework for building Singer taps and targets",
  "license": null,
  "license_expression": "Apache-2.0",
  "home_page": "https://sdk.meltano.com/en/latest/",
  "home_page_source": "project_urls.homepage",
  "maintainer": null,
  "author": null,
  "repository": "https://github.com/meltano/sdk",
  "repository_source": "project_urls.repository",
  "download": null,
  "download_source": null,
  "pub_date": 1774895469,
  "project_urls": {
    "Slack": "https://meltano.com/slack",
    "Documentation": "https://sdk.meltano.com/en/latest/",
    "Twitter": "https://twitter.com/meltanodata/",
    "Homepage": "https://sdk.meltano.com/en/latest/",
    "Issue Tracker": "https://github.com/meltano/sdk/issues",
    "Repository": "https://github.com/meltano/sdk",
    "Changelog": "https://github.com/meltano/sdk/blob/main/CHANGELOG.md",
    "Youtube": "https://www.youtube.com/meltano"
  },
  "has_github_actions": true,
  "has_gitlab_pipeline": null,
  "has_dependabot": true,
  "has_pyproject_toml": true,
  "has_setup_py": false,
  "has_setup_cfg": false
}