{
  "name": "xrag-temporal",
  "version": "0.1.0",
  "summary": "Time-aware uncertainty for RAG — temporal decay of evidence confidence using Subjective Logic",
  "license": "MIT",
  "license_expression": null,
  "home_page": null,
  "home_page_source": null,
  "maintainer": null,
  "author": "Muntaser Syed",
  "repository": "https://github.com/jemsbhai/subjective-logic-rag",
  "repository_source": "project_urls.repository",
  "download": null,
  "download_source": null,
  "pub_date": 1776201264,
  "project_urls": {
    "Repository": "https://github.com/jemsbhai/subjective-logic-rag"
  },
  "has_github_actions": false,
  "has_gitlab_pipeline": null,
  "has_dependabot": false,
  "has_pyproject_toml": true,
  "has_setup_py": false,
  "has_setup_cfg": false
}