{
  "name": "schedview",
  "version": "0.23.0",
  "summary": "Tools for visualization of Rubin Observatory's scheduler status, strategy and progress on LSST.",
  "license": null,
  "license_expression": null,
  "home_page": null,
  "home_page_source": null,
  "maintainer": null,
  "author": "Eric Neilsen, Lynne Jones, Eman Ali, Alice Serene",
  "repository": "https://github.com/lsst/schedview",
  "repository_source": "project_urls.repository",
  "download": null,
  "download_source": null,
  "pub_date": 1775773523,
  "project_urls": {
    "documentation": "https://schedview.lsst.io",
    "repository": "https://github.com/lsst/schedview"
  },
  "has_github_actions": true,
  "has_gitlab_pipeline": null,
  "has_dependabot": false,
  "has_pyproject_toml": true,
  "has_setup_py": false,
  "has_setup_cfg": true
}