{
  "name": "sandlerprops",
  "version": "0.4.0",
  "summary": "A python interface to the pure-component properties database for Sandler 5e",
  "license": null,
  "license_expression": null,
  "home_page": null,
  "maintainer": null,
  "maintainer_email": null,
  "author": null,
  "author_email": "Cameron F Abrams <cfa22@drexel.edu>",
  "pub_date": 1768403162,
  "project_urls": {
    "homepage": null,
    "repository": null,
    "github": null
  },
  "has_github_actions": null,
  "has_gitlab_pipeline": null
}