{
  "name": "kitconcept.seo",
  "version": "2.1.2",
  "summary": "SEO optimizations plugin for Plone",
  "license": "GPL version 2",
  "license_expression": null,
  "home_page": "https://pypi.python.org/pypi/kitconcept.seo",
  "home_page_source": "project_urls.homepage",
  "maintainer": null,
  "author": "kitconcept GmbH",
  "repository": "https://github.com/kitconcept/kitconcept.seo",
  "repository_source": "project_urls.source",
  "download": null,
  "download_source": null,
  "pub_date": 1769448613,
  "project_urls": {
    "Homepage": "https://pypi.python.org/pypi/kitconcept.seo",
    "Tracker": "https://github.com/kitconcept/kitconcept.seo/issues",
    "PyPI": "https://pypi.python.org/pypi/kitconcept.seo",
    "Source": "https://github.com/kitconcept/kitconcept.seo"
  },
  "has_github_actions": true,
  "has_gitlab_pipeline": null,
  "has_dependabot": false,
  "has_pyproject_toml": true,
  "has_setup_py": true,
  "has_setup_cfg": false
}