{
  "name": "vigilai-scan",
  "version": "0.1.0",
  "summary": "Read-only AWS compliance baseline scanner — 15 checks mapped to SOC 2 criteria, with the Terraform fix for every failure",
  "license": "MIT",
  "license_expression": null,
  "home_page": null,
  "home_page_source": null,
  "maintainer": null,
  "author": "VigilAI",
  "repository": null,
  "repository_source": null,
  "download": null,
  "download_source": null,
  "pub_date": 1783725717,
  "project_urls": {},
  "has_github_actions": null,
  "has_gitlab_pipeline": null,
  "has_dependabot": null,
  "has_pyproject_toml": null,
  "has_setup_py": null,
  "has_setup_cfg": null
}