{
  "name": "vordr",
  "version": "0.2.0",
  "summary": "Guardião dos servidores — monitoramento de status, recursos, custo/expiração e segurança de hosts Linux via SSH.",
  "license": "MIT",
  "license_expression": null,
  "home_page": "https://github.com/gusta-ve/vordr",
  "home_page_source": "project_urls.homepage",
  "maintainer": null,
  "author": "Gustavo Almeida",
  "repository": "https://github.com/gusta-ve/vordr",
  "repository_source": "project_urls.repository",
  "download": null,
  "download_source": null,
  "pub_date": 1782396579,
  "project_urls": {
    "Issues": "https://github.com/gusta-ve/vordr/issues",
    "Homepage": "https://github.com/gusta-ve/vordr",
    "Repository": "https://github.com/gusta-ve/vordr"
  },
  "has_github_actions": true,
  "has_gitlab_pipeline": null,
  "has_dependabot": false,
  "has_pyproject_toml": true,
  "has_setup_py": false,
  "has_setup_cfg": false
}