{
  "name": "elara-core",
  "version": "0.15.1",
  "summary": "Persistent presence, mood, memory, and self-awareness for AI assistants",
  "license": null,
  "license_expression": "LicenseRef-BSL-1.1",
  "home_page": "https://elara.navigatorbuilds.com",
  "home_page_source": "project_urls.homepage",
  "maintainer": null,
  "author": "Nenad Vasić",
  "repository": "https://github.com/navigatorbuilds/elara-core",
  "repository_source": "project_urls.repository",
  "download": null,
  "download_source": null,
  "pub_date": 1771708457,
  "project_urls": {
    "Issues": "https://github.com/navigatorbuilds/elara-core/issues",
    "Repository": "https://github.com/navigatorbuilds/elara-core",
    "Documentation": "https://github.com/navigatorbuilds/elara-core#readme",
    "Homepage": "https://elara.navigatorbuilds.com"
  },
  "has_github_actions": true,
  "has_gitlab_pipeline": null,
  "has_dependabot": true,
  "has_pyproject_toml": true,
  "has_setup_py": false,
  "has_setup_cfg": false
}