{
  "name": "service-identity",
  "version": "26.1.0",
  "summary": "Service identity verification for pyOpenSSL & cryptography.",
  "license": null,
  "license_expression": "MIT",
  "home_page": null,
  "home_page_source": null,
  "maintainer": null,
  "author": null,
  "repository": "https://github.com/pyca/service-identity",
  "repository_source": "project_urls.github",
  "download": null,
  "download_source": null,
  "pub_date": 1780142693,
  "project_urls": {
    "GitHub": "https://github.com/pyca/service-identity",
    "Twitter": "https://twitter.com/hynek",
    "Funding": "https://github.com/sponsors/hynek",
    "Mastodon": "https://mastodon.social/@hynek",
    "Changelog": "https://service-identity.readthedocs.io/en/stable/changelog.html",
    "Documentation": "https://service-identity.readthedocs.io/",
    "Tidelift": "https://tidelift.com/subscription/pkg/pypi-service-identity?utm_source=pypi-service-identity&utm_medium=pypi"
  },
  "has_github_actions": true,
  "has_gitlab_pipeline": null,
  "has_dependabot": true,
  "has_pyproject_toml": true,
  "has_setup_py": false,
  "has_setup_cfg": false
}