{
  "name": "cdxcore",
  "version": "0.1.45",
  "summary": "Basic Python Tools; upgraded cdxbasics",
  "license": null,
  "license_expression": "MIT",
  "home_page": null,
  "maintainer": null,
  "maintainer_email": null,
  "author": null,
  "author_email": "Hans Buehler <github@buehler.london>",
  "pub_date": 1768519859,
  "project_urls": {
    "homepage": "https://github.com/hansbuehler/cdxcore",
    "repository": null,
    "github": null
  },
  "has_github_actions": true,
  "has_gitlab_pipeline": null
}