{
  "name": "attodi",
  "version": "0.0.10",
  "summary": "Minimalistic DI library for python.",
  "license": null,
  "license_expression": "GPL-3.0",
  "home_page": "https://github.com/LostSavannah/attodi",
  "home_page_source": "project_urls.homepage",
  "maintainer": null,
  "author": null,
  "repository": "https://github.com/LostSavannah/attodi",
  "repository_source": "project_urls.homepage",
  "download": null,
  "download_source": null,
  "pub_date": 1784114909,
  "project_urls": {
    "Homepage": "https://github.com/LostSavannah/attodi",
    "Issues": "https://github.com/LostSavannah/attodi/issues"
  },
  "has_github_actions": true,
  "has_gitlab_pipeline": null,
  "has_dependabot": false,
  "has_pyproject_toml": true,
  "has_setup_py": false,
  "has_setup_cfg": false
}