{
  "name": "shesha-geometry",
  "version": "0.2.0",
  "summary": "Self-consistency metrics for representational stability analysis",
  "license": "MIT",
  "license_expression": null,
  "home_page": "https://github.com/prashantcraju/shesha",
  "home_page_source": "project_urls.homepage",
  "maintainer": null,
  "author": null,
  "repository": "https://github.com/prashantcraju/shesha",
  "repository_source": "project_urls.repository",
  "download": null,
  "download_source": null,
  "pub_date": 1774038530,
  "project_urls": {
    "Repository": "https://github.com/prashantcraju/shesha",
    "Documentation": "https://github.com/prashantcraju/shesha#readme",
    "Issues": "https://github.com/prashantcraju/shesha/issues",
    "Homepage": "https://github.com/prashantcraju/shesha"
  },
  "has_github_actions": true,
  "has_gitlab_pipeline": null,
  "has_dependabot": false,
  "has_pyproject_toml": true,
  "has_setup_py": false,
  "has_setup_cfg": false
}