{
  "name": "inspire-dojson",
  "version": "63.2.33",
  "summary": "INSPIRE-specific rules to transform from MARCXML to JSON and back.",
  "license": "GPLv3",
  "license_expression": null,
  "home_page": "https://github.com/inspirehep/inspire-dojson",
  "home_page_source": "project_urls.homepage",
  "maintainer": null,
  "author": "CERN",
  "repository": "https://github.com/inspirehep/inspire-dojson",
  "repository_source": "project_urls.homepage",
  "download": null,
  "download_source": null,
  "pub_date": 1771417831,
  "project_urls": {
    "Homepage": "https://github.com/inspirehep/inspire-dojson"
  },
  "has_github_actions": true,
  "has_gitlab_pipeline": null,
  "has_dependabot": false,
  "has_pyproject_toml": false,
  "has_setup_py": true,
  "has_setup_cfg": true
}