{
  "name": "openmanage-mcp-server",
  "version": "1.0.0",
  "summary": "MCP server for Dell OpenManage Enterprise server management",
  "license": null,
  "license_expression": "MIT",
  "home_page": "https://github.com/clearminds/openmanage-mcp-server",
  "home_page_source": "project_urls.homepage",
  "maintainer": null,
  "author": "Clearminds AB",
  "repository": "https://github.com/clearminds/openmanage-mcp-server",
  "repository_source": "project_urls.repository",
  "download": null,
  "download_source": null,
  "pub_date": 1771403919,
  "project_urls": {
    "Issues": "https://github.com/clearminds/openmanage-mcp-server/issues",
    "Repository": "https://github.com/clearminds/openmanage-mcp-server",
    "Homepage": "https://github.com/clearminds/openmanage-mcp-server"
  },
  "has_github_actions": true,
  "has_gitlab_pipeline": null,
  "has_dependabot": false,
  "has_pyproject_toml": true,
  "has_setup_py": false,
  "has_setup_cfg": false
}