{
  "name": "xmldiffreport",
  "version": "0.1.0",
  "summary": "N-way structural & semantic XML diff that generates human-readable Markdown reports, driven by per-dialect recipes (Control-M, sitemaps, and more).",
  "license": "MIT",
  "license_expression": null,
  "home_page": "https://github.com/bilouro/xmldiffreport",
  "home_page_source": "project_urls.homepage",
  "maintainer": null,
  "author": "Victor H. Bilouro",
  "repository": "https://github.com/bilouro/xmldiffreport",
  "repository_source": "project_urls.repository",
  "download": null,
  "download_source": null,
  "pub_date": 1780569329,
  "project_urls": {
    "Documentation": "https://bilouro.github.io/xmldiffreport/",
    "Homepage": "https://github.com/bilouro/xmldiffreport",
    "Issues": "https://github.com/bilouro/xmldiffreport/issues",
    "Repository": "https://github.com/bilouro/xmldiffreport",
    "Changelog": "https://github.com/bilouro/xmldiffreport/blob/main/CHANGELOG.md"
  },
  "has_github_actions": true,
  "has_gitlab_pipeline": null,
  "has_dependabot": false,
  "has_pyproject_toml": true,
  "has_setup_py": false,
  "has_setup_cfg": false
}