{
  "name": "clonex",
  "version": "1.0.0",
  "summary": "CloneX: GitHub multi-repo maintenance tool with CLI, GUI, and MCP entrypoints",
  "license": null,
  "license_expression": "MIT",
  "home_page": "https://github.com/qiao-925/CloneX",
  "home_page_source": "project_urls.homepage",
  "maintainer": null,
  "author": "qiao-925",
  "repository": "https://github.com/qiao-925/CloneX",
  "repository_source": "project_urls.homepage",
  "download": null,
  "download_source": null,
  "pub_date": 1776995631,
  "project_urls": {
    "Homepage": "https://github.com/qiao-925/CloneX"
  },
  "has_github_actions": true,
  "has_gitlab_pipeline": null,
  "has_dependabot": false,
  "has_pyproject_toml": true,
  "has_setup_py": false,
  "has_setup_cfg": false
}