{
  "name": "baseshift",
  "version": "2.5.0",
  "summary": "Baseshift CLI - Database clone management with Tailscale connectivity",
  "license": "BSD 2-Clause License",
  "license_expression": null,
  "home_page": "https://baseshift.io",
  "home_page_source": "project_urls.homepage",
  "maintainer": null,
  "author": null,
  "repository": "https://baseshift.io",
  "repository_source": "project_urls.homepage",
  "download": null,
  "download_source": null,
  "pub_date": 1772027474,
  "project_urls": {
    "Homepage": "https://baseshift.io"
  },
  "has_github_actions": null,
  "has_gitlab_pipeline": null,
  "has_dependabot": null,
  "has_pyproject_toml": null,
  "has_setup_py": null,
  "has_setup_cfg": null
}