{
  "name": "timeit-decorator",
  "version": "2.2.1",
  "summary": "A versatile timing decorator",
  "license": null,
  "license_expression": "GPL-3.0-or-later",
  "home_page": "https://github.com/jubnl/timeit_decorator",
  "home_page_source": "project_urls.homepage",
  "maintainer": null,
  "author": null,
  "repository": "https://github.com/jubnl/timeit_decorator",
  "repository_source": "project_urls.repository",
  "download": null,
  "download_source": null,
  "pub_date": 1773321262,
  "project_urls": {
    "Documentation": "https://github.com/jubnl/timeit_decorator/blob/main/README.md",
    "Homepage": "https://github.com/jubnl/timeit_decorator",
    "Issues": "https://github.com/jubnl/timeit_decorator/issues",
    "Repository": "https://github.com/jubnl/timeit_decorator"
  },
  "has_github_actions": true,
  "has_gitlab_pipeline": null,
  "has_dependabot": false,
  "has_pyproject_toml": true,
  "has_setup_py": false,
  "has_setup_cfg": false
}