{
  "name": "xycore",
  "version": "1.0.2",
  "summary": "The XY primitive — cryptographic verification for any system.",
  "license": "MIT",
  "license_expression": null,
  "home_page": "https://pruv.dev",
  "home_page_source": "project_urls.homepage",
  "maintainer": null,
  "author": null,
  "repository": "https://github.com/mintingpressbuilds/pruv",
  "repository_source": "project_urls.repository",
  "download": null,
  "download_source": null,
  "pub_date": 1771569874,
  "project_urls": {
    "Repository": "https://github.com/mintingpressbuilds/pruv",
    "Documentation": "https://docs.pruv.dev",
    "Homepage": "https://pruv.dev"
  },
  "has_github_actions": true,
  "has_gitlab_pipeline": null,
  "has_dependabot": false,
  "has_pyproject_toml": true,
  "has_setup_py": false,
  "has_setup_cfg": false
}