{
  "name": "coqpit-config",
  "version": "0.2.3",
  "summary": "Simple (maybe too simple), light-weight config management through python data-classes.",
  "license": "MIT",
  "home_page": null,
  "maintainer": null,
  "maintainer_email": "Enno Hermann <enno.hermann@gmail.com>",
  "author": null,
  "author_email": "Eren Gölge <egolge@coqui.ai>",
  "pub_date": 1767786386,
  "project_urls": {
    "homepage": null,
    "repository": "https://github.com/idiap/coqui-ai-coqpit",
    "github": null
  }
}