{
  "name": "dedoku",
  "version": "1.1.0",
  "summary": "A pure-Python Sudoku solver that uses only human-style logical deduction techniques (no backtracking).",
  "license": "MIT",
  "license_expression": null,
  "home_page": null,
  "home_page_source": null,
  "maintainer": null,
  "author": null,
  "repository": "https://github.com/n36l3c7/Dedoku",
  "repository_source": "project_urls.repository",
  "download": null,
  "download_source": null,
  "pub_date": 1784326577,
  "project_urls": {
    "Changelog": "https://github.com/n36l3c7/Dedoku/blob/main/CHANGELOG.md",
    "Documentation": "https://n36l3c7.github.io/Dedoku/",
    "Repository": "https://github.com/n36l3c7/Dedoku"
  },
  "has_github_actions": true,
  "has_gitlab_pipeline": null,
  "has_dependabot": false,
  "has_pyproject_toml": true,
  "has_setup_py": false,
  "has_setup_cfg": false
}