{
  "name": "deeplake",
  "version": "4.5.3",
  "summary": "Data Lake for Multi-Modal AI Search",
  "license": null,
  "license_expression": null,
  "home_page": null,
  "home_page_source": null,
  "maintainer": null,
  "author": "activeloop.ai",
  "repository": "https://github.com/activeloopai/deeplake",
  "repository_source": "project_urls.source",
  "download": null,
  "download_source": null,
  "pub_date": 1772060755,
  "project_urls": {
    "Documentation": "https://docs.deeplake.ai/",
    "Source": "https://github.com/activeloopai/deeplake"
  },
  "has_github_actions": true,
  "has_gitlab_pipeline": null,
  "has_dependabot": false,
  "has_pyproject_toml": false,
  "has_setup_py": false,
  "has_setup_cfg": false
}