{
  "name": "TopDownHockey-Scraper",
  "version": "6.1.32",
  "summary": "The TopDownHockey Scraper",
  "license": "MIT",
  "license_expression": null,
  "home_page": "https://github.com/TopDownHockey/TopDownHockey_Scraper",
  "maintainer": null,
  "author": "Patrick Bacon",
  "repository": "https://github.com/TopDownHockey/TopDownHockey_Scraper",
  "repository_source": "project_urls.homepage",
  "pub_date": 1768983226,
  "project_urls": {
    "Bug Tracker": "https://github.com/TopDownHockey/TopDownHockey_Scraper/issues",
    "Homepage": "https://github.com/TopDownHockey/TopDownHockey_Scraper"
  },
  "has_github_actions": true,
  "has_gitlab_pipeline": null,
  "has_dependabot": false
}