{
  "name": "pygubu",
  "version": "0.40",
  "summary": "A simple GUI builder for the python tkinter module",
  "license": null,
  "license_expression": "MIT",
  "home_page": null,
  "home_page_source": null,
  "maintainer": null,
  "author": null,
  "repository": "https://github.com/alejandroautalan/pygubu",
  "repository_source": "project_urls.source",
  "download": null,
  "download_source": null,
  "pub_date": 1769321127,
  "project_urls": {
    "Documentation": "https://github.com/alejandroautalan/pygubu#readme",
    "Issues": "https://github.com/alejandroautalan/pygubu/issues",
    "Source": "https://github.com/alejandroautalan/pygubu"
  },
  "has_github_actions": false,
  "has_gitlab_pipeline": null,
  "has_dependabot": false,
  "has_pyproject_toml": true,
  "has_setup_py": true,
  "has_setup_cfg": false
}