{
  "name": "python-durable",
  "version": "0.1.1",
  "summary": "Lightweight workflow durability for Python — make any async workflow resumable after crashes with just a decorator.",
  "license": null,
  "license_expression": "MIT",
  "home_page": null,
  "home_page_source": null,
  "maintainer": null,
  "author": "Willem",
  "repository": "https://github.com/WillemDeGroef/python-durable",
  "repository_source": "project_urls.repository",
  "download": null,
  "download_source": null,
  "pub_date": 1772276359,
  "project_urls": {
    "Repository": "https://github.com/WillemDeGroef/python-durable"
  },
  "has_github_actions": true,
  "has_gitlab_pipeline": null,
  "has_dependabot": false,
  "has_pyproject_toml": true,
  "has_setup_py": false,
  "has_setup_cfg": false
}