{
  "name": "leann",
  "version": "0.3.7",
  "summary": "LEANN - The smallest vector index in the world. RAG Everything with LEANN!",
  "license": "MIT",
  "license_expression": null,
  "home_page": null,
  "home_page_source": null,
  "maintainer": null,
  "author": "LEANN Team",
  "repository": "https://github.com/yichuan-w/LEANN",
  "repository_source": "project_urls.repository",
  "download": null,
  "download_source": null,
  "pub_date": 1773005730,
  "project_urls": {
    "Issues": "https://github.com/yichuan-w/LEANN/issues",
    "Repository": "https://github.com/yichuan-w/LEANN"
  },
  "has_github_actions": true,
  "has_gitlab_pipeline": null,
  "has_dependabot": false,
  "has_pyproject_toml": true,
  "has_setup_py": false,
  "has_setup_cfg": false
}