{
  "name": "ldcov",
  "version": "0.5.0",
  "summary": "A Python package for efficient linkage disequilibrium calculation with covariate adjustment",
  "license": "MIT License",
  "license_expression": null,
  "home_page": "https://github.com/mkanai/ldcov",
  "home_page_source": "project_urls.homepage",
  "maintainer": null,
  "author": null,
  "repository": "https://github.com/mkanai/ldcov",
  "repository_source": "project_urls.homepage",
  "download": null,
  "download_source": null,
  "pub_date": 1783203043,
  "project_urls": {
    "Homepage": "https://github.com/mkanai/ldcov",
    "Bug Tracker": "https://github.com/mkanai/ldcov/issues",
    "Changelog": "https://github.com/mkanai/ldcov/blob/master/CHANGELOG.md"
  },
  "has_github_actions": true,
  "has_gitlab_pipeline": null,
  "has_dependabot": false,
  "has_pyproject_toml": true,
  "has_setup_py": false,
  "has_setup_cfg": false
}