{
  "name": "ChameleonIQ",
  "version": "1.0.5",
  "summary": "A tool for NEMA NU 2-2018 Image Quality analysis.",
  "license": null,
  "license_expression": "MIT AND (Apache-2.0 OR BSD-2-Clause)",
  "home_page": null,
  "maintainer": null,
  "author": "Edwing Ulin-Briseno",
  "pub_date": 1768572789,
  "project_urls": {
    "homepage": "https://github.com/EdAlita/ChameleonIQ/wiki",
    "repository": null,
    "github": null
  },
  "has_github_actions": true,
  "has_gitlab_pipeline": null,
  "has_dependabot": false
}