{
  "name": "chelombus",
  "version": "0.2.0",
  "summary": "Billion-scale molecular clustering and visualization using Product Quantization and nested TMAPs.",
  "license": "MIT",
  "license_expression": null,
  "home_page": "https://github.com/afloresep/chelombus",
  "home_page_source": "project_urls.homepage",
  "maintainer": null,
  "author": "Alejandro Flores",
  "repository": "https://github.com/afloresep/chelombus",
  "repository_source": "project_urls.repository",
  "download": null,
  "download_source": null,
  "pub_date": 1770028999,
  "project_urls": {
    "Homepage": "https://github.com/afloresep/chelombus",
    "Repository": "https://github.com/afloresep/chelombus",
    "Documentation": "https://chelombus.gdb.tools"
  },
  "has_github_actions": true,
  "has_gitlab_pipeline": null,
  "has_dependabot": false,
  "has_pyproject_toml": true,
  "has_setup_py": true,
  "has_setup_cfg": false
}