{
  "name": "superrtl",
  "version": "0.2.0",
  "summary": "Verilog EDA 工具的 MCP/CLI 客户端 - 一键安装，开箱即用",
  "license": "MIT",
  "license_expression": null,
  "home_page": "https://github.com/RTL-Agent/SuperRTL",
  "home_page_source": "project_urls.homepage",
  "maintainer": null,
  "author": null,
  "repository": "https://github.com/RTL-Agent/SuperRTL",
  "repository_source": "project_urls.repository",
  "download": null,
  "download_source": null,
  "pub_date": 1781363625,
  "project_urls": {
    "Issues": "https://github.com/RTL-Agent/SuperRTL/issues",
    "Changelog": "https://github.com/RTL-Agent/SuperRTL/blob/main/CHANGELOG.md",
    "Documentation": "https://github.com/RTL-Agent/SuperRTL#readme",
    "Repository": "https://github.com/RTL-Agent/SuperRTL",
    "Homepage": "https://github.com/RTL-Agent/SuperRTL"
  },
  "has_github_actions": false,
  "has_gitlab_pipeline": null,
  "has_dependabot": false,
  "has_pyproject_toml": null,
  "has_setup_py": null,
  "has_setup_cfg": null
}