{
  "name": "ai-ahg6wf",
  "version": "1.0.0",
  "summary": "AI训练数据的价值：如何为机器学习提供高质量数据资源",
  "license": "MIT",
  "license_expression": null,
  "home_page": "https://mebelplovdiv.com",
  "home_page_source": "project_urls.homepage",
  "maintainer": null,
  "author": null,
  "repository": "https://mebelplovdiv.com",
  "repository_source": "project_urls.homepage",
  "download": null,
  "download_source": null,
  "pub_date": 1777705313,
  "project_urls": {
    "Homepage": "https://mebelplovdiv.com"
  },
  "has_github_actions": null,
  "has_gitlab_pipeline": null,
  "has_dependabot": null,
  "has_pyproject_toml": null,
  "has_setup_py": null,
  "has_setup_cfg": null
}