{
  "name": "ai-cloudscraper",
  "version": "3.7.0",
  "summary": "Enhanced Python library to bypass Cloudflare's anti-bot protection with cutting-edge anti-detection technologies, including TLS fingerprinting, ML optimization, behavioral simulation, and 10 industrial-strength bypass strategies.",
  "license": "MIT",
  "home_page": "https://github.com/zinzied/ai-cloudscraper",
  "maintainer": null,
  "maintainer_email": "Zied Boughdir <ziedboughdir@gmail.com>",
  "author": "Zied Boughdir",
  "author_email": "Zied Boughdir <zied.boughdir@gmail.com>",
  "pub_date": 1767542552
}