{
  "name": "streetlevel",
  "version": "0.12.6",
  "summary": "Download panoramas and metadata from Street View, Look Around, and more",
  "license": null,
  "license_expression": "MIT",
  "home_page": "https://github.com/sk-zk/streetlevel",
  "home_page_source": "project_urls.homepage",
  "maintainer": null,
  "author": null,
  "repository": "https://github.com/sk-zk/streetlevel",
  "repository_source": "project_urls.homepage",
  "download": null,
  "download_source": null,
  "pub_date": 1778152754,
  "project_urls": {
    "Homepage": "https://github.com/sk-zk/streetlevel",
    "Bug Tracker": "https://github.com/sk-zk/streetlevel/issues"
  },
  "has_github_actions": true,
  "has_gitlab_pipeline": null,
  "has_dependabot": false,
  "has_pyproject_toml": true,
  "has_setup_py": false,
  "has_setup_cfg": false
}