{
  "name": "igdl",
  "version": "0.2.0",
  "summary": "CLI tool to download images and videos from Instagram posts",
  "license": "MIT",
  "license_expression": null,
  "home_page": "https://github.com/viviciu/igdl",
  "home_page_source": "project_urls.homepage",
  "maintainer": null,
  "author": "viviciu",
  "repository": "https://github.com/viviciu/igdl",
  "repository_source": "project_urls.repository",
  "download": null,
  "download_source": null,
  "pub_date": 1783729977,
  "project_urls": {
    "Repository": "https://github.com/viviciu/igdl",
    "Homepage": "https://github.com/viviciu/igdl"
  },
  "has_github_actions": false,
  "has_gitlab_pipeline": null,
  "has_dependabot": false,
  "has_pyproject_toml": true,
  "has_setup_py": false,
  "has_setup_cfg": false
}