{
  "name": "genaiscope",
  "version": "0.7.0",
  "summary": "Local-first AI memory, observability, evaluation, safety, and optimization toolkit for GenAI applications.",
  "license": null,
  "license_expression": "MIT",
  "home_page": "https://github.com/TravelXML/genaiscope",
  "home_page_source": "project_urls.homepage",
  "maintainer": "GenAIScope Contributors",
  "author": "Sapan Mohanty",
  "repository": "https://github.com/TravelXML/genaiscope",
  "repository_source": "project_urls.repository",
  "download": null,
  "download_source": null,
  "pub_date": 1782479154,
  "project_urls": {
    "Documentation": "https://travelxml.github.io/genaiscope",
    "Changelog": "https://github.com/TravelXML/genaiscope/releases",
    "Issues": "https://github.com/TravelXML/genaiscope/issues",
    "Repository": "https://github.com/TravelXML/genaiscope",
    "Homepage": "https://github.com/TravelXML/genaiscope"
  },
  "has_github_actions": true,
  "has_gitlab_pipeline": null,
  "has_dependabot": false,
  "has_pyproject_toml": true,
  "has_setup_py": false,
  "has_setup_cfg": false
}