{
  "name": "genro-bag",
  "version": "0.7.1",
  "summary": "Modernized bag system for the Genropy framework - hierarchical data container with XML serialization",
  "license": null,
  "license_expression": "Apache-2.0",
  "home_page": null,
  "maintainer": null,
  "author": "Genropy Team",
  "pub_date": 1768640109,
  "project_urls": {
    "homepage": "https://github.com/genropy/genro-bag",
    "repository": "https://github.com/genropy/genro-bag",
    "github": null
  },
  "has_github_actions": true,
  "has_gitlab_pipeline": null,
  "has_dependabot": false
}