{
  "name": "cs-ascii-art",
  "version": "20260228",
  "summary": "Utilities to assist with ASCII art such as railroad diagrams; since these use Unicode box drawing characters and are better for diagrams such as railroad diagrams, this is neither ASCII nor art.",
  "license": null,
  "license_expression": null,
  "home_page": null,
  "home_page_source": null,
  "maintainer": null,
  "author": null,
  "repository": "https://github.com/cameron-simpson/css/blob/main/lib/python/cs/ascii_art.py",
  "repository_source": "project_urls.source",
  "download": null,
  "download_source": null,
  "pub_date": 1772271971,
  "project_urls": {
    "Monorepo Hg/Mercurial Mirror": "https://hg.sr.ht/~cameron-simpson/css",
    "Monorepo Git Mirror": "https://github.com/cameron-simpson/css",
    "Source": "https://github.com/cameron-simpson/css/blob/main/lib/python/cs/ascii_art.py",
    "MonoRepo Commits": "https://bitbucket.org/cameron_simpson/css/commits/branch/main"
  },
  "has_github_actions": false,
  "has_gitlab_pipeline": null,
  "has_dependabot": false,
  "has_pyproject_toml": false,
  "has_setup_py": false,
  "has_setup_cfg": false
}