{
  "name": "google-shopping-type",
  "version": "1.2.0",
  "summary": "Google Shopping Type API client library",
  "license": "Apache 2.0",
  "home_page": "https://github.com/googleapis/google-cloud-python/tree/main/packages/google-shopping-type",
  "maintainer": null,
  "maintainer_email": null,
  "author": "Google LLC",
  "author_email": "googleapis-packages@google.com",
  "pub_date": 1767890620,
  "project_urls": {
    "homepage": "https://github.com/googleapis/google-cloud-python/tree/main/packages/google-shopping-type",
    "repository": null,
    "github": null
  }
}